{"name":"build-javascript","namedChunkGroups":{"polyfill":{"name":"polyfill","assets":[{"name":"webpack-runtime-24f089d9c63adeda9cad.js","size":4085},{"name":"polyfill-1caa278ea0fd60c8892b.js","size":85848}],"filteredAssets":0,"assetsSize":89933,"filteredAuxiliaryAssets":2,"auxiliaryAssetsSize":223965},"app":{"name":"app","assets":[{"name":"webpack-runtime-24f089d9c63adeda9cad.js","size":4085},{"name":"framework-e120579c0057d454c43b.js","size":129761},{"name":"styles.7de9cef9004c1325fa5a.css","size":26171},{"name":"fb7d5399-450f1c4836787276edd2.js","size":604614},{"name":"app-14dd279c9e9b4c5ee20d.js","size":197221}],"filteredAssets":0,"assetsSize":961852,"filteredAuxiliaryAssets":4,"auxiliaryAssetsSize":3293119},"component---src-pages-404-js":{"name":"component---src-pages-404-js","assets":[{"name":"component---src-pages-404-js-0199e61b3b62b687174a.js","size":813}],"filteredAssets":0,"assetsSize":813,"filteredAuxiliaryAssets":1,"auxiliaryAssetsSize":1886},"component---src-pages-about-tsx":{"name":"component---src-pages-about-tsx","assets":[{"name":"component---src-pages-about-tsx-b823ed106a097f69202e.js","size":1190}],"filteredAssets":0,"assetsSize":1190,"filteredAuxiliaryAssets":2,"auxiliaryAssetsSize":974777},"component---src-pages-index-tsx":{"name":"component---src-pages-index-tsx","assets":[{"name":"component---src-pages-index-tsx-fea55d99b9d731556006.js","size":1248}],"filteredAssets":0,"assetsSize":1248,"filteredAuxiliaryAssets":1,"auxiliaryAssetsSize":2738},"component---src-pages-investments-tsx":{"name":"component---src-pages-investments-tsx","assets":[{"name":"component---src-pages-investments-tsx-e27be1eec63392679a6b.js","size":1466}],"filteredAssets":0,"assetsSize":1466,"filteredAuxiliaryAssets":1,"auxiliaryAssetsSize":3221},"component---src-pages-nf-ts-tsx":{"name":"component---src-pages-nf-ts-tsx","assets":[{"name":"component---src-pages-nf-ts-tsx-be5d5ee574434610b366.js","size":1431}],"filteredAssets":0,"assetsSize":1431,"filteredAuxiliaryAssets":1,"auxiliaryAssetsSize":3551}},"assetsByChunkName":{"polyfill":["webpack-runtime-24f089d9c63adeda9cad.js","polyfill-1caa278ea0fd60c8892b.js"],"app":["webpack-runtime-24f089d9c63adeda9cad.js","framework-e120579c0057d454c43b.js","styles.7de9cef9004c1325fa5a.css","fb7d5399-450f1c4836787276edd2.js","app-14dd279c9e9b4c5ee20d.js"],"component---src-pages-404-js":["component---src-pages-404-js-0199e61b3b62b687174a.js"],"component---src-pages-about-tsx":["component---src-pages-about-tsx-b823ed106a097f69202e.js"],"component---src-pages-index-tsx":["component---src-pages-index-tsx-fea55d99b9d731556006.js"],"component---src-pages-investments-tsx":["component---src-pages-investments-tsx-e27be1eec63392679a6b.js"],"component---src-pages-nf-ts-tsx":["component---src-pages-nf-ts-tsx-be5d5ee574434610b366.js"]},"childAssetsByChunkName":{}}